quapp_dwave_ocean/__init__.py
quapp_dwave_ocean/async_tasks/__init__.py
quapp_dwave_ocean/async_tasks/d_wave_ocean_circuit_export_task.py
quapp_dwave_ocean/component/__init__.py
quapp_dwave_ocean/component/backend/__init__.py
quapp_dwave_ocean/component/backend/d_wave_ocean_invocation.py
quapp_dwave_ocean/component/backend/d_wave_ocean_job_fetching.py
quapp_dwave_ocean/factory/__init__.py
quapp_dwave_ocean/factory/d_wave_device_factory.py
quapp_dwave_ocean/factory/d_wave_handler_factory.py
quapp_dwave_ocean/factory/d_wave_provider_factory.py
quapp_dwave_ocean/handler/__init__.py
quapp_dwave_ocean/handler/invocation_handler.py
quapp_dwave_ocean/handler/job_fetching_handler.py
quapp_dwave_ocean/model/__init__.py
quapp_dwave_ocean/model/device/__init__.py
quapp_dwave_ocean/model/device/d_wave_device.py
quapp_dwave_ocean/model/device/d_wave_hybrid_device.py
quapp_dwave_ocean/model/device/d_wave_system_device.py
quapp_dwave_ocean/model/device/quapp_d_wave_device.py
quapp_dwave_ocean/model/provider/__init__.py
quapp_dwave_ocean/model/provider/d_wave_system_provider.py
quapp_dwave_ocean/model/provider/quapp_d_wave_provider.py
quapp_dwave_ocean-0.0.1.dev3.dist-info/licenses/LICENSE
quapp_dwave_ocean-0.0.1.dev3.dist-info/METADATA
quapp_dwave_ocean-0.0.1.dev3.dist-info/WHEEL
quapp_dwave_ocean-0.0.1.dev3.dist-info/top_level.txt
quapp_dwave_ocean-0.0.1.dev3.dist-info/RECORD
