Metadata-Version: 2.4
Name: quapp-dwave-ocean
Version: 0.0.1.dev3
Summary: Quapp D-Wave Ocean library supporting Quapp Platform for Quantum Computing
Author-email: "CITYNOW Co. Ltd. " <corp@citynow.vn>
License: The MIT License (MIT)
Project-URL: Homepage, https://citynow.asia/
Keywords: quapp,quapp-dwave-ocean,dwave-ocean,quantum
Classifier: License :: OSI Approved :: MIT License
Classifier: Programming Language :: Python
Classifier: Programming Language :: Python :: 3
Requires-Python: >=3.7
License-File: LICENSE
Requires-Dist: quapp-common==0.0.11.dev7
Requires-Dist: dwave-cloud-client==0.13.4
Requires-Dist: dwave-system==1.30.0
Requires-Dist: dwave-samplers==1.5.0
Requires-Dist: dimod==0.12.20
Requires-Dist: numpy==2.2.4
Provides-Extra: dev
Requires-Dist: black; extra == "dev"
Requires-Dist: bumpver; extra == "dev"
Requires-Dist: isort; extra == "dev"
Requires-Dist: pip-tools; extra == "dev"
Requires-Dist: pytest; extra == "dev"
Dynamic: license-file
